product_details/__init__.py
product_details/models.py
product_details/settings_defaults.py
product_details/storage.py
product_details/utils.py
product_details/json/.all.json.last_modified
product_details/json/.devedition.json.last_modified
product_details/json/.firefox.json.last_modified
product_details/json/.firefox_history_development_releases.json.last_modified
product_details/json/.firefox_history_major_releases.json.last_modified
product_details/json/.firefox_history_stability_releases.json.last_modified
product_details/json/.firefox_primary_builds.json.last_modified
product_details/json/.firefox_versions.json.last_modified
product_details/json/.gitignore
product_details/json/.languages.json.last_modified
product_details/json/.last_update
product_details/json/.mobile_android.json.last_modified
product_details/json/.mobile_details.json.last_modified
product_details/json/.mobile_history_development_releases.json.last_modified
product_details/json/.mobile_history_major_releases.json.last_modified
product_details/json/.mobile_history_stability_releases.json.last_modified
product_details/json/.mobile_versions.json.last_modified
product_details/json/.pinebuild.json.last_modified
product_details/json/.thunderbird.json.last_modified
product_details/json/.thunderbird_beta_builds.json.last_modified
product_details/json/.thunderbird_history_development_releases.json.last_modified
product_details/json/.thunderbird_history_major_releases.json.last_modified
product_details/json/.thunderbird_history_stability_releases.json.last_modified
product_details/json/.thunderbird_primary_builds.json.last_modified
product_details/json/.thunderbird_versions.json.last_modified
product_details/json/all.json
product_details/json/devedition.json
product_details/json/firefox.json
product_details/json/firefox_history_development_releases.json
product_details/json/firefox_history_major_releases.json
product_details/json/firefox_history_stability_releases.json
django_mozilla_product_details-1.0.3.dist-info/LICENSE
django_mozilla_product_details-1.0.3.dist-info/METADATA
django_mozilla_product_details-1.0.3.dist-info/WHEEL
django_mozilla_product_details-1.0.3.dist-info/top_level.txt
django_mozilla_product_details-1.0.3.dist-info/RECORD
